aspider/__init__.py
aspider/__main__.py
aspider/aspider.py
aspider/crawling.py
aspider/outputing.py
aspider/reporting.py
aspider/routeing.py
aspider/util.py
example/__init__.py
example/bus_spider.py
example/db.py
example/parser.py
example/prog.py
aspider-0.1.2.dist-info/LICENSE.md
aspider-0.1.2.dist-info/METADATA
aspider-0.1.2.dist-info/WHEEL
aspider-0.1.2.dist-info/entry_points.txt
aspider-0.1.2.dist-info/top_level.txt
aspider-0.1.2.dist-info/RECORD
