Metadata-Version: 2.1
Name: aspider
Version: 0.1.2
Summary: a spider using asyncio
Home-page: https://github.com/gxtrobot/aspider
Author: gxtrobot
Author-email: gxtrobot@gmail.com
License: BSD
Download-URL: https://github.com/gxtrobot/aspider/tarball/0.1.2
Platform: UNKNOWN
Classifier: Development Status :: 3 - Alpha
Classifier: Intended Audience :: Developers
Classifier: Programming Language :: Python :: 3
Classifier: Programming Language :: Python :: 3.6
Requires-Python: >=3.6
Requires-Dist: aiohttp
Requires-Dist: requests-html
